ansiblevarchecker/__init__.py
ansiblevarchecker/__main__.py
ansiblevarchecker/file_handler.py
ansiblevarchecker/logger.py
ansiblevarchecker/parser.py
ansiblevarchecker/yaml_constructor.py
ansiblevarchecker/jinja/__init__.py
ansiblevarchecker/jinja/config.py
ansiblevarchecker/jinja/core.py
ansiblevarchecker/jinja/exceptions.py
ansiblevarchecker/jinja/macro.py
ansiblevarchecker/jinja/mergers.py
ansiblevarchecker/jinja/model.py
ansiblevarchecker/jinja/visitors/__init__.py
ansiblevarchecker/jinja/visitors/expr.py
ansiblevarchecker/jinja/visitors/stmt.py
ansiblevarchecker/jinja/visitors/util.py
ansiblevarchecker/scope/__init__.py
ansiblevarchecker/scope/access_type.py
ansiblevarchecker/scope/error_record.py
ansiblevarchecker/scope/scope.py
ansiblevarchecker-0.0.2.dist-info/METADATA
ansiblevarchecker-0.0.2.dist-info/WHEEL
ansiblevarchecker-0.0.2.dist-info/entry_points.txt
ansiblevarchecker-0.0.2.dist-info/top_level.txt
ansiblevarchecker-0.0.2.dist-info/RECORD
