Metadata-Version: 2.1
Name: ansiblevarchecker
Version: 0.0.2
Summary: Variable checker for ansible playbooks
Home-page: https://github.com/KlutzyBubbles/ansible-var-checker
Author: KlutzyBubbles
Author-email: LTzilantois@gmail.com
Project-URL: Documentation, https://ansible_var_checker.readthedocs.io
Project-URL: Source, https://github.com/KlutzyBubbles/ansible-var-checker
Project-URL: Issues, https://github.com/KlutzyBubbles/ansible-var-checker/issues
Classifier: Development Status :: 3 - Alpha
Classifier: Intended Audience :: Developers
Classifier: Operating System :: OS Independent
Classifier: Programming Language :: Python
Classifier: Programming Language :: Python :: 2.7
Classifier: Programming Language :: Python :: 3.6
Classifier: Programming Language :: Python :: 3.7
Classifier: Programming Language :: Python :: 3.8
Classifier: Programming Language :: Python :: 3.9
Classifier: Programming Language :: Python :: 3.10
Classifier: Programming Language :: Python :: Implementation :: CPython
Requires-Python: >=2.7, !=3.0.*, !=3.1.*, !=3.2.*, !=3.3.*, !=3.4.*, !=3.5.*, !=3.6.*
Requires-Dist: ansible (==2.9.*)
Requires-Dist: jinja2 (~=2.11)
Requires-Dist: six (~=1.14)
